colored_glog.py
colored_glog-1.3.0.dist-info/DESCRIPTION.rst
colored_glog-1.3.0.dist-info/METADATA
colored_glog-1.3.0.dist-info/RECORD
colored_glog-1.3.0.dist-info/WHEEL
colored_glog-1.3.0.dist-info/metadata.json
colored_glog-1.3.0.dist-info/top_level.txt
