Metadata-Version: 2.0
Name: colored-glog
Version: 1.3.0
Summary: Colored Google-style logging wrapper for Python.
Home-page: https://github.com/xiaoxq/colored-glog
Author: Xiangquan Xiao
Author-email: xiaoxiangquan@gmail.com
License: BSD
Platform: any
Classifier: Programming Language :: Python
Classifier: Development Status :: 4 - Beta
Classifier: Intended Audience :: Developers
Classifier: License :: OSI Approved :: BSD License
Classifier: Topic :: System :: Logging
Classifier: Topic :: Software Development :: Libraries :: Python Modules
Requires-Dist: termcolor
